[{"entityId":"demo-ent-0","name":"Ray Delgado","kind":"person","count":25},{"entityId":"demo-ent-1","name":"Gloria Bennett","kind":"person","count":8},{"entityId":"demo-ent-2","name":"Eleanor Meyer","kind":"person","count":6},{"entityId":"demo-ent-3","name":"Cook County Dept. of Transportation & Highways","kind":"person","count":92},{"entityId":"demo-ent-4","name":"IDOT District 1 — Constituent Services","kind":"person","count":85},{"entityId":"demo-ent-5","name":"Priya Nair","kind":"person","count":66},{"entityId":"demo-ent-6","name":"Proviso Township Assessor","kind":"person","count":61},{"entityId":"demo-ent-7","name":"Metra — UP-W Community Relations","kind":"person","count":51},{"entityId":"demo-ent-8","name":"Bellwood Public Library","kind":"person","count":43},{"entityId":"demo-ent-9","name":"Proviso Township School District 209","kind":"person","count":41},{"entityId":"demo-ent-10","name":"Village of Maywood — Mutual Aid","kind":"person","count":34},{"entityId":"demo-ent-11","name":"Cook County Clerk","kind":"person","count":30},{"entityId":"demo-ent-12","name":"Marcus Webb","kind":"person","count":14},{"entityId":"demo-ent-13","name":"Lamont Franklin","kind":"person","count":9},{"entityId":"demo-ent-14","name":"Lucia Nguyen","kind":"person","count":9},{"entityId":"demo-ent-15","name":"Walter Reynolds","kind":"person","count":9},{"entityId":"demo-ent-16","name":"Aaliyah Simmons","kind":"person","count":8},{"entityId":"demo-ent-17","name":"Denise Carter","kind":"person","count":8},{"entityId":"demo-ent-18","name":"Alicia Vargas","kind":"person","count":8},{"entityId":"demo-ent-19","name":"Omar Hayes","kind":"person","count":8},{"entityId":"demo-ent-20","name":"Nadia Marshall","kind":"person","count":8},{"entityId":"demo-ent-21","name":"Dwayne Wilson","kind":"person","count":8},{"entityId":"demo-ent-22","name":"Felix Flores","kind":"person","count":8},{"entityId":"demo-ent-23","name":"Regina Santos","kind":"person","count":8},{"entityId":"demo-ent-24","name":"Lamont Davis","kind":"person","count":8},{"entityId":"demo-ent-25","name":"Zoe Howard","kind":"person","count":8},{"entityId":"demo-ent-26","name":"Nathan Taylor","kind":"person","count":8},{"entityId":"demo-ent-27","name":"Jorge Rojas","kind":"person","count":7},{"entityId":"demo-ent-28","name":"Antoine Brooks","kind":"person","count":7},{"entityId":"demo-ent-29","name":"Miguel Parker","kind":"person","count":7},{"entityId":"demo-ent-30","name":"Bellwood PD — Watch Commander","kind":"department","count":1253},{"entityId":"demo-ent-31","name":"Bellwood Fire Dept. — Shift Commander","kind":"department","count":969},{"entityId":"demo-ent-32","name":"Inspector Dale Brackett","kind":"official","count":488},{"entityId":"demo-ent-33","name":"Bellwood PD — Records Bureau","kind":"official","count":434},{"entityId":"demo-ent-34","name":"Frank DiMeo","kind":"official","count":420},{"entityId":"demo-ent-35","name":"Chief Lillian Vasquez","kind":"department","count":334},{"entityId":"demo-ent-36","name":"Karen Whitfield","kind":"official","count":235},{"entityId":"demo-ent-37","name":"Officer Reggie Banks","kind":"official","count":212},{"entityId":"demo-ent-38","name":"David Okafor","kind":"official","count":129},{"entityId":"demo-ent-39","name":"Tom Reyes","kind":"official","count":119}]